{"model_relationships_07-morph-one.md":"BCLeyOOS","collections_has.md":"D1zGm5G9","collections_isempty.md":"F4cBbOXL","collections_dd.md":"BY5oDt4v","collections_wherenotinstrict.md":"CxO37ZJv","collections_countby.md":"DALhx2Jd","collections_contains.md":"HXekBjxE","collections_diffassocusing.md":"BtzmrQX4","collections_diffassoc.md":"KNmA3Swn","collections_duplicates.md":"sinW18SU","collections_intersectbykeys.md":"BnUu32ir","collections_wrap.md":"DrpoIo18","collections_duplicatesstrict.md":"BMz649zq","collections_reverse.md":"B6rk46_O","collections_crossjoin.md":"DFgImx7g","collections_examples_markdown-format.md":"CC0tkjgS","collections_sliding.md":"DzOf4a_R","collections_examples_order-info-summary.md":"BDFimWIr","collections_wherebetween.md":"C09-WiZM","collections_select.md":"B8tvZX79","collections_doesntcontain.md":"CK2dQclS","collections_ensure.md":"Cn1LB9bs","model_relationships_03-has-one-of-many.md":"Ctu84B6F","collections_examples_map-format.md":"vUGQ9zYw","collections_unwrap.md":"CbesnMnc","collections_reject.md":"PvvGo4PQ","collections_replace.md":"B2hRUu1B","collections_search.md":"Dr468MEt","collections_wherenotbetween.md":"CbW5ni5V","collections_shift.md":"C1-tRhjv","collections_shuffle.md":"DHbM3MND","collections_skip.md":"fd9-MfIE","collections_skipuntil.md":"BZYz24V5","collections_examples_using-reduce-create-lookup-array.md":"D0VgWsHQ","collections_skipwhile.md":"C7ppYK0l","collections_slice.md":"DopKGYXY","model_relationships_04-has-one-through.md":"iY6g0e7M","collections_sortbydesc.md":"CKgr-8dh","collections_takewhile.md":"wtS7iF2B","collections_tap.md":"CZ_31in4","collections_times.md":"Bo9kVgow","collections_toarray.md":"B1pyxNj7","collections_undot.md":"DvLP6PyU","collections_union.md":"D_0YxWoA","collections_unique.md":"Dtqiejtg","collections_uniquestrict.md":"B9z3kwhr","collections_examples_using-sum-method.md":"CEYBNGbP","collections_unless.md":"B_ypHSwh","collections_whereinstanceof.md":"B1cW-HiW","collections_except.md":"DYMWBzZr","collections_flatmap.md":"DIJr0JE8","collections_tojson.md":"DSrFyNYK","collections_containsstrict.md":"D35mUMex","collections_reduce.md":"DpX7Vo_j","collections_combine.md":"BqBMJmDq","collections_replacerecursive.md":"BU_-d7u9","collections_filter.md":"BH-6Cyiu","model_relationships_09-one-of-many.md":"DDAY20on","others_readme.md":"BDDYW75q","collections_flatten.md":"DotVC97E","collections_diff.md":"MavtnYjq","collections_firstorfail.md":"Dfb4JU3O","collections_forget.md":"uiTpQKFG","collections_push.md":"BExhOvxw","others_helpers_arrays.md":"CGXlbs9d","collections_forpage.md":"hPfqnrlV","model_relationships_readme.md":"Iq-pXKc4","collections_every.md":"Dx-2s2xH","partials_validation.md":"BUXgBZap","collections_wherenotin.md":"C7HDUpij","partials_views.md":"Dk_LnhHi","partials_model.md":"eoO_h8cw","others_helpers_fluent.md":"BEcRrnPl","others_helpers_paths.md":"C7adeBJ-","packages_spatie_laravel-data.md":"rJGZh089","packages_spatie_laravel-login-link.md":"DrhopLcQ","partials_readme.md":"L1Dx_eyt","collections_pad.md":"Blu6FpRk","partials_factories.md":"BH1-CS-p","collections_isnotempty.md":"BpFSU9D3","index.md":"C4dKCgUC","others_helpers_numbers.md":"DI4yasy_","collections_each.md":"BsCyVjuV","collections_dump.md":"ChDQe6N1","collections_avg.md":"Dpm4sn0q","collections_put.md":"BSfsNMqE","collections_random.md":"BM_iZUOt","collections_wherenotnull.md":"tILb4kgH","collections_diffusing.md":"DJzRfe0V","model_relationships_08-morph-many.md":"CP71agw1","collections_diffkeysusing.md":"BiDT5jy5","collections_diffkeys.md":"DGt4YJim","collections_chunk.md":"BZTKDO_C","collections_reducespread.md":"C9tlXNQf","collections_transform.md":"BSGDaO_0","collections_examples_readme.md":"BoEmxIwz","model_relationships_10-morph-to-many.md":"BEBfi6aG","collections_first.md":"DhMevFQ2","collections_count.md":"kkCqJmVs","collections_all.md":"CjIfE-u2","others_artisan-command-to-generate-views-in-laravel.md":"DHz1vKU4","others_custom-collection-for-laravel-eloquent-model.md":"BrYoMhEE","collections_firstwhere.md":"CDWeb8M0","collections_implode.md":"BEWmmavJ","model_relationships_02-has-many.md":"CDbXQcH8","collections_intersect.md":"BS0D2bJO","collections_groupby.md":"DPII_W61","collections_examples_get-the-corresponding-key-by-value.md":"4BA1VDRe","collections_flip.md":"H0aGZmPZ","others_custom-query-builder-for-laravel-eloquent-model.md":"-YDPdfnv","model_relationships_05-has-many-through.md":"Cw27dZet","collections_hasany.md":"CkquzhMD","collections_get.md":"BKQG2LXo","others_helpers_carbon.md":"B0D37Lka","collections_after.md":"BO8RrN14","partials_urls.md":"Cv0Fuzhv","collections_macro.md":"DIsscr7H","packages_laravel_pint.md":"BOTr-4qy","packages_others_index.md":"DiMcPUXs","collections_containsoneitem.md":"CfuxWfxN","tips_index.md":"KRl9b_qH","tips_optimize-factory-database-batch-insert.md":"YxE9G1vQ","tips_modular-laravel.md":"QYMV1PyI","tips_process-large-csv-files-with-laravel-using-simple-excel.md":"SSxBCldU","tips_reuse-the-environment-variable-value.md":"CD2u6riD","model_some-tips-for-optimize-database-queries.md":"DMKhOKdK","collections_zip.md":"Bcdo7krY","model_index.md":"nHSmQYXi","others_helpers_urls.md":"ClAukd14","collections_keyby.md":"B2_iZQ54","collections_splitin.md":"DomvBIvA","collections_sum.md":"BZNmpjn_","collections_value.md":"BFc0ehSD","others_laravel-create-custom-facade-test-demo.md":"C62y66W7","collections_split.md":"BKW05zzE","others_laravel-import-custom-function-file.md":"BD8CnTtM","partials_model-relations.md":"34JhxOHF","collections_where.md":"DuC_ThCk","model_relationships_06-belongs-to-many.md":"D58lwV-c","collections_max.md":"BuugTSJx","tips_db-models-and-eloquent.md":"DX_I3VSv","collections_mapwithkeys.md":"DvBe_WnI","collections_whereinstrict.md":"BN10UnNA","others_macros.md":"D5nXp7Rw","collections_mode.md":"8cimh1Ri","others_unit-test-laravel-api-pest-framework.md":"C9nRjY2t","collections_sortby.md":"bj5pihvS","collections_partition.md":"Ccqp4Ttt","others_using-custom-exceptions-to-write-better-and-clearer-code.md":"C0NRqsRh","collections_pipe.md":"C5iZX38O","collections_eachspread.md":"DouqbXzg","collections_pluck.md":"BmluyI7N","packages_index.md":"yuOd4-IP","collections_concat.md":"BCMXV2Cr","collections_pull.md":"BX0aRPif","collections_pop.md":"DNJVNcdF","collections_collect.md":"D756n1QI","collections_examples_format-calculate-the-data-of-the-two-arrays.md":"DCG1_rZ9","packages_laravel_readme.md":"CnQEAtpX","packages_laravel_index.md":"D9p42dHQ","collections_map.md":"BM4_vFDb","collections_maptodictionary.md":"BqE3Jteh","collections_merge.md":"QfthQOsW","collections_nth.md":"DHv2mli0","collections_only.md":"DSwPnQb7","collections_prepend.md":"uqHCZQDy","readme.md":"D70ztpr5","collections_before.md":"Dak6LpX6","collections_wherestrict.md":"hpybjsXR","collections_wherein.md":"DRGlAYu5","collections_take.md":"9qWI-ypG","collections_pipethrough.md":"CShhoX58","collections_sortkeys.md":"BRUKlLj7","collections_lazy.md":"XDK9smcS","collections_make.md":"DVOfFeno","model_relationships_01-has-one.md":"lNFf6q0f","collections_index.md":"DQv2vw_H","collections_mapspread.md":"DTqZSOkk","collections_mapinto.md":"CUPv5J9w","collections_takeuntil.md":"BHUBrfHk","collections_examples_format-github-events-score.md":"CW8la3lT","partials_testing.md":"DLHIfL8V","packages_others_readme.md":"E5zDlVgX","collections_chunkwhile.md":"0InXSbYV","collections_maptogroups.md":"BMqRI7gg","collections_mergerecursive.md":"DA8vFkwW","collections_median.md":"CnqufchJ","packages_spatie_laravel-backup.md":"ByJJil4S","packages_others_saloon.md":"DFk0DWL2","collections_keys.md":"BVHbeYSo","collections_last.md":"DNCR6yS-","packages_others_sushi.md":"C4qRs_GE","packages_spatie_readme.md":"kZxZePtc","collections_sort.md":"OE1v-vLT","packages_spatie_index.md":"C3LpF12F","tips_readme.md":"Dbg8rmQl","packages_readme.md":"D9IEqmrW","packages_others_missing-livewire-assertions.md":"Dn92tlTL","packages_others_eloquent-query-cache.md":"rwS1oszx","collections_sortdesc.md":"CFc4AFO1","partials_migrations.md":"D5eo0wS8","others_whats-new-in-laravel-11.md":"Dcr_0air","collections_values.md":"OM0jDGeK","packages_laravel_prompts.md":"CTJQECjG","others_helpers_sleep.md":"CHzFytOM","collections_whenempty.md":"WUvnTeYF","collections_join.md":"BHh4qBK0","collections_pipeinto.md":"Ci2ka_d3","others_helpers_stringable.md":"BJE4AqV_","model_laravel-model-events.md":"CephXbSB","collections_min.md":"B4Ke6jAJ","others_scroll-to-validation-error-in-laravel-using-alpinejs.md":"CNiuLWWB","collections_whennotempty.md":"CBvNs2lx","collections_when.md":"BrFTSXPO","model_laravel-model-observers.md":"VLoGDnsv","collections_sole.md":"DIXp4p6R","packages_laravel_pail.md":"tFhe8rn-","collections_wherenull.md":"TnJ1dM0k","partials_routing.md":"ClTMYMaw","model_laravel-model-caching.md":"Bow5wm9d","collections_collapse.md":"C53pl9oe","collections_sortkeysdesc.md":"B3zg_qiR","collections_splice.md":"C4G-J0EU","others_helpers_strings.md":"DisoYiYL","collections_sortkeysusing.md":"CU3UUgUE"}
